{
  "collectionName": "components_shared_simple_cards",
  "info": {
    "displayName": "SimpleCard",
    "icon": "archive"
  },
  "options": {},
  "attributes": {
    "Image": {
      "type": "media",
      "multiple": false,
      "allowedTypes": [
        "images",
        "files",
        "videos",
        "audios"
      ]
    },
    "Title": {
      "type": "string"
    },
    "Description": {
      "type": "blocks"
    },
    "Link": {
      "type": "component",
      "component": "shared.link",
      "repeatable": false
    }
  },
  "config": {}
}
